ntnx_objects_py_client/__init__.py
ntnx_objects_py_client/api_client.py
ntnx_objects_py_client/api_response.py
ntnx_objects_py_client/configuration.py
ntnx_objects_py_client/custom_retry.py
ntnx_objects_py_client/rest.py
ntnx_objects_py_client/api/__init__.py
ntnx_objects_py_client/api/object_stores_api.py
ntnx_objects_py_client/api/stats_api.py
ntnx_objects_py_client/models/__init__.py
ntnx_objects_py_client/models/OneOfcommon/__init__.py
ntnx_objects_py_client/models/OneOfcommon/v1/__init__.py
ntnx_objects_py_client/models/OneOfcommon/v1/config/KVPairvalue.py
ntnx_objects_py_client/models/OneOfcommon/v1/config/__init__.py
ntnx_objects_py_client/models/OneOfobjects/__init__.py
ntnx_objects_py_client/models/OneOfobjects/v4/__init__.py
ntnx_objects_py_client/models/OneOfobjects/v4/config/CreateCertificateApiResponsedata.py
ntnx_objects_py_client/models/OneOfobjects/v4/config/CreateObjectstoreApiResponsedata.py
ntnx_objects_py_client/models/OneOfobjects/v4/config/DeleteObjectstoreApiResponsedata.py
ntnx_objects_py_client/models/OneOfobjects/v4/config/GetCaApiResponsedata.py
ntnx_objects_py_client/models/OneOfobjects/v4/config/GetCertificateApiResponsedata.py
ntnx_objects_py_client/models/OneOfobjects/v4/config/GetObjectstoreApiResponsedata.py
ntnx_objects_py_client/models/OneOfobjects/v4/config/ListCertificatesApiResponsedata.py
ntnx_objects_py_client/models/OneOfobjects/v4/config/ListObjectstoresApiResponsedata.py
ntnx_objects_py_client/models/OneOfobjects/v4/config/UpdateObjectstoreApiResponsedata.py
ntnx_objects_py_client/models/OneOfobjects/v4/config/__init__.py
ntnx_objects_py_client/models/OneOfobjects/v4/error/ErrorResponseerror.py
ntnx_objects_py_client/models/OneOfobjects/v4/error/__init__.py
ntnx_objects_py_client/models/OneOfobjects/v4/stats/GetObjectstoreStatsApiResponsedata.py
ntnx_objects_py_client/models/OneOfobjects/v4/stats/__init__.py
ntnx_objects_py_client/models/common/__init__.py
ntnx_objects_py_client/models/common/v1/__init__.py
ntnx_objects_py_client-4.0.1.dist-info/LICENSE.txt
ntnx_objects_py_client-4.0.1.dist-info/METADATA
ntnx_objects_py_client-4.0.1.dist-info/WHEEL
ntnx_objects_py_client-4.0.1.dist-info/top_level.txt
ntnx_objects_py_client-4.0.1.dist-info/RECORD
