Metadata-Version: 2.1
Name: ntnx-objects-py-client
Version: 4.0.1
Summary: Nutanix Objects Storage Management APIs
Home-page: 
Author-email: sdk@nutanix.com
Keywords: Nutanix,v4,SDK,Nutanix Objects Storage Management APIs
License-File: LICENSE.txt
Requires-Dist: urllib3 ~=1.26
Requires-Dist: six ~=1.16
Requires-Dist: certifi <=2023.11.17,>=2020.4.5.1
Requires-Dist: python-dateutil ~=2.8
Requires-Dist: pysocks ~=1.7
